{"properties":[{"Key":"ParentID","DisplayName":"ParentID","FieldType":"String","DefaultValue":"","Description":"The ParentID of this div","List":""},{"Key":"Language","DisplayName":"Language","FieldType":"String","DefaultValue":"vb","Description":"Language","List":"css|html|js|vb"},{"Key":"Caption","DisplayName":"Caption","FieldType":"String","DefaultValue":"Source Code","Description":"Caption","List":""},{"Key":"CodeType","DisplayName":"Code Type","FieldType":"String","DefaultValue":"default","Description":"Code Type","List":"card|default"},{"Key":"FileName","DisplayName":"File Name","FieldType":"String","DefaultValue":"code.bas","Description":"File Name","List":""},{"Key":"FontName","DisplayName":"Font Name","FieldType":"String","DefaultValue":"","Description":"Font Name","List":""},{"Key":"FontSize","DisplayName":"Font Size","FieldType":"String","DefaultValue":"","Description":"Font Size","List":""},{"Key":"Visible","DisplayName":"Visible","FieldType":"Boolean","DefaultValue":"True","Description":"If visible.","List":""},{"Key":"MarginAXYTBLR","DisplayName":"Margins","FieldType":"String","DefaultValue":"a=?; x=?; y=?; t=?; b=?; l=?; r=?","Description":"Margins A-X-Y-T-B-L-R","List":""},{"Key":"PaddingAXYTBLR","DisplayName":"Paddings","FieldType":"String","DefaultValue":"a=?; x=?; y=?; t=?; b=?; l=?; r=?","Description":"Paddings A-X-Y-T-B-L-R","List":""},{"Key":"RawClasses","DisplayName":"Classes","FieldType":"String","DefaultValue":"","Description":"Classes added to the HTML tag.","List":""},{"Key":"RawStyles","DisplayName":"Styles","FieldType":"String","DefaultValue":"","Description":"Styles added to the HTML tag. Must be a json String- use =","List":""},{"Key":"RawAttributes","DisplayName":"Attributes","FieldType":"String","DefaultValue":"","Description":"Attributes added to the HTML tag. Must be a json String- use =","List":""}],"events":[{"name":"Action (item As String)"}],"methods":[{"name":"DesignerCreateView","signature":"DesignerCreateView (Target As BANanoElement, Props As Map)"},{"name":"Initialize","signature":"Initialize (CallBack As Object, cName As String, EventName As String)"},{"name":"AddMockUpCode","signature":"AddMockUpCode(mCallback As Object, ParentID As String, ID As String, lang As String)"},{"name":"AddMockUpCodeCard","signature":"AddMockUpCodeCard(mCallback As Object, ParentID As String, ID As String, lang As String, sTitle As String)"},{"name":"AssignElement","signature":"AssignElement(mCallBack As Object, ID As String)"},{"name":"AddActionButton","signature":"AddActionButton(btnID As String, btnCaption As String, btnColor As String) As SDUIButton"},{"name":"AddActionButtonIcon","signature":"AddActionButtonIcon(btnID As String, sIcon As String, btnColor As String) As SDUIButton"},{"name":"setCaption","signature":"setCaption(l As String)"},{"name":"Enable","signature":"Enable"},{"name":"Disable","signature":"Disable"},{"name":"Show","signature":"Show"},{"name":"Hide","signature":"Hide"},{"name":"Clear","signature":"Clear"},{"name":"AddCode","signature":"AddCode(cl As String)"},{"name":"PasteFromClipBoard","signature":"PasteFromClipBoard"},{"name":"CopyToClipboard","signature":"CopyToClipboard(txt As String)"},{"name":"Refresh","signature":"Refresh"},{"name":"RefreshRaw","signature":"RefreshRaw"},{"name":"setValue","signature":"setValue(s As String)"},{"name":"getValue","signature":"getValue As String"},{"name":"Download","signature":"Download(FileName As String)"},{"name":"On","signature":"On(event As String, CallBack As Object, MethodName As String)"},{"name":"getHere","signature":"getHere As String"},{"name":"getName","signature":"getName As String"},{"name":"setFontSize","signature":"setFontSize(fs As String)"},{"name":"setFontName","signature":"setFontName(fs As String)"},{"name":"AddToParent","signature":"AddToParent(targetID As String, props As Map)"}]}